[
  {
    "q": "つまり",
    "r": "つまり",
    "m": "즉, 요컨대, 결국",
    "u": "부사",
    "e": "1. 父の 弟は、つまり 叔父です。\n2. 明日は 休みです。つまり、今日 全部 終わらなければ なりません。\n3. お金が ありません。つまり、買えません。",
    "tip": "[한자 풀이] 동사 '詰まる(막히다, 가득 차다)'에서 유래했습니다. 이야기가 끝까지 차올라 결론에 도달했다는 의미를 담고 있습니다."
  },
  {
    "q": "頑張る",
    "r": "가んばる",
    "m": "열심히 하다, 힘내다, 버티다",
    "u": "동사(1그룹)",
    "e": "1. 明日の 試験を 頑張ります。\n2. 最後まで 諦めないで 頑張って ください。\n3. 日本語の 勉強を 毎日 頑張って います。",
    "tip": "[한자 풀이] 頑(완고할 완) + 張(베풀 장). 자신의 의지나 태도를 완고하게 펴서 끝까지 밀고 나간다는 뜻입니다."
  },
  {
    "q": "大事だ",
    "r": "だいじだ",
    "m": "중요하다, 소중하다",
    "u": "나형용사",
    "e": "1. 健康가 一番 大事です。\n2. 大事な 書류를 無くしました。\n3. 家族は 私に とって とても 大事です。",
    "tip": "[한자 풀이] 大(큰 대) + 事(일 사). 원래 국가의 중대한 사건을 의미했으며, 그만큼 신중하고 중요하게 다루어야 한다는 뜻에서 유래했습니다."
  },
  {
    "q": "増やす",
    "r": "ふやす",
    "m": "늘리다, 불리다",
    "u": "동사(1그룹)",
    "e": "1. 貯金を 増やす ために 頑張ります。\n2. 単語の 数を 増야したいです。\n3. アルバイトを して 収入を 増やしました。",
    "tip": "[한자 풀이] 土(흙 토) + 曾(거듭 증). 흙을 거듭 쌓아 올려서 양을 불린다는 의미입니다."
  },
  {
    "q": "光る",
    "r": "ひかる",
    "m": "빛나다, 반짝이다",
    "u": "동사(1그룹)",
    "e": "1. 星が 綺麗に 光って います。\n2. 磨いた ダイヤモンドは 光ります。\n3. 暗い ところで 猫の 目が 光ります。",
    "tip": "[한자 풀이] 光(빛 광). 불(火) 아래에 사람이 서 있는 모습으로, 사람이 횃불을 들고 '빛나다'라는 뜻을 나타냅니다."
  },
  {
    "q": "火事",
    "r": "かじ",
    "m": "화재, 불",
    "u": "명사",
    "e": "1. 火事に 気を つけて ください。\n2. 近くで 火事が ありました。\n3. 火事は 恐ろしいです。",
    "tip": "[한자 풀이] 火(불 화) + 事(일 사). 말 그대로 '불이 난 사건'을 뜻합니다."
  },
  {
    "q": "家事",
    "r": "かじ",
    "m": "집안일, 가사",
    "u": "명사",
    "e": "1. 毎日 家事を して います。\n2. 父も 家事を 手伝います。\n3. 料理は 大変な 家事です。",
    "tip": "[한자 풀이] 家(집 가) + 事(일 사). '집안에서 일어나는 모든 일'을 뜻합니다."
  },
  {
    "q": "怪我をする",
    "r": "けがをする",
    "m": "다치다, 부상을 입다",
    "u": "동사(3그룹)",
    "e": "1. 足に 怪我を しました。\n2. 危ないですから、怪我を しないで ください。\n3. 試合で 怪我を して 休みました。",
    "tip": "[한자 풀이] 怪(괴이할 괴) + 我(나 아). 본래 '나에게 일어난 괴이한 일'이라는 뜻에서 부상을 의미하게 되었습니다."
  },
  {
    "q": "暗い",
    "r": "くらい",
    "m": "어둡다, 우울하다",
    "u": "이형용사",
    "e": "1. 部屋が 暗いので、電気を つけます。\n2. 外は もう 暗く なりました。\n3. 彼は 性격이 少し 暗いです。",
    "tip": "[한자 풀이] 日(날 일) + 音(소리 음). 해가 져서 소리만 들리는 '어두운' 상태를 형상화했습니다."
  },
  {
    "q": "黒い",
    "r": "くろい",
    "m": "검다, 까맣다",
    "u": "이형용사",
    "e": "1. 今日は 黒い 服を 着て います。\n2. 彼は 髪が 黒いです。\n3. 黒い カバンを 샀습니다.",
    "tip": "[한자 풀이] 黒(검을 흑). 불(火) 위에 연기가 나고 창문에 그을음(土)이 묻은 모습을 나타냅니다."
  },
  {
    "q": "運転",
    "r": "うんてん",
    "m": "운전",
    "u": "명사 / 동사(3그룹)",
    "e": "1. 車を 運転します。\n2. 父は 運転が 上手です。\n3. 毎日 運転して います。",
    "tip": "[한자 풀이] 運(움직일 운) + 転(굴릴 전). '수레나 바퀴를 굴려 움직인다'는 뜻입니다."
  },
  {
    "q": "進学",
    "r": "しんがく",
    "m": "진학",
    "u": "명사 / 동사(3그룹)",
    "e": "1. 大学に 進学したいです。\n2. 進学の 準備を します。\n3. どこに 進学しますか。",
    "tip": "[한자 풀이] 進(나아갈 진) + 学(배울 학). '배움을 위해 더 높은 단계로 나아간다'는 뜻입니다."
  },
  {
    "q": "進行",
    "r": "しんこう",
    "m": "진행",
    "u": "명사 / 동사(3그룹)",
    "e": "1. プロジェクトを 進行します。\n2. 仕事は 順調に 進行して います。\n3. 司회자가 会議を 進行します。",
    "tip": "[한자 풀이] 進(나아갈 진) + 行(갈 행). '앞으로 나아가며 행한다'는 뜻입니다."
  },
  {
    "q": "早い",
    "r": "はやい",
    "m": "(시간이) 빠르다, 이르다",
    "u": "이형용사",
    "e": "1. 朝 早く 起きました。\n2. 今日は 帰るのが 早いです。\n3. まだ 諦めるのは 早いです。",
    "tip": "[한자 풀이] 早(일찍 조). 해(日)가 지평선(十) 위로 막 떠오른 이른 아침을 의미합니다."
  },
  {
    "q": "速い",
    "r": "はやい",
    "m": "(속도가) 빠르다",
    "u": "이형용사",
    "e": "1. この 車は とても 速いです。\n2. 足が 速い 人은 誰ですか。\n3. 走るのが 速いですね。",
    "tip": "[한자 풀이] 速(빠를 속). 책받침(辶-가다) + 묶을 속(束). 짐을 묶어 신속하게 이동한다는 뜻입니다."
  },
  {
    "q": "吹く",
    "r": "ふく",
    "m": "불다",
    "u": "동사(1그룹)",
    "e": "1. 窓から 涼しい 風が 吹いて います。\n2. 熱い スープを 吹いて 冷まします。\n3. 彼女は 毎日 フルートを 吹く 練習を します。",
    "tip": "[한자 풀이] 口(입 구) + 欠(하품 흠). 입을 크게 벌리고 숨을 내뿜는 모습에서 유래했습니다."
  },
  {
    "q": "結ぶ",
    "r": "むすぶ",
    "m": "묶다, 매다, 결성하다",
    "u": "동사(1그룹)",
    "e": "1. 靴の 紐を 結びます。\n2. 二인은 固い 約束を 結びました。\n3. 点と 点을 線으로 結びます。",
    "tip": "[한자 풀이] 糸(실 사) + 吉(좋을 길). 실을 좋게 엮어서 단단히 묶는다는 뜻입니다."
  },
  {
    "q": "続く",
    "r": "つづく",
    "m": "계속되다, 이어지다",
    "u": "동사(1그룹)",
    "e": "1. 雨が 三日 続いて います。\n2. この 道는 隣의 町에 続いて います。\n3. 勉強を 続ける ことは 大事です。",
    "tip": "[한자 풀이] 糸(실 사) + 賣(팔 매). 실이 끊어지지 않고 계속해서 이어진다는 뜻입니다."
  },
  {
    "q": "経験",
    "r": "けいけん",
    "m": "경험",
    "u": "명사 / 동사(3그룹)",
    "e": "1. 海外で いろいろな 経験を しました。\n2. 経験は 宝物です。\n3. 仕事の 経験が 豊かなです。",
    "tip": "[한자 풀이] 経(지날 경) + 験(시험할 험). 시간이 지나며 직접 겪고 시험해 보는 일을 뜻합니다."
  },
  {
    "q": "練習",
    "r": "れんしゅう",
    "m": "연습",
    "u": "명사 / 동사(3그룹)",
    "e": "1. 毎日 ピアノを 練習します。\n2. 練習すれば 上手に なります。\n3. 会話の 練習を 頑張りましょう。",
    "tip": "[한자 풀이] 練(익힐 련) + 習(익힐 습). 실을 불에 달구어 익히고, 어린 새가 날갯짓을 반복하듯 익히는 것입니다."
  },
  {
    "q": "終わる",
    "r": "おわる",
    "m": "마치다, 끝나다",
    "u": "동사(1그룹)",
    "e": "1. 今日の 仕事は 全部 終わりました。\n2. 会議が 終わったら、すぐ 連絡します。\n3. この 本を 読み 終わりました。",
    "tip": "[한자 풀이] 糸(실 사) + 冬(겨울 동). 실의 매듭과 계절의 끝인 겨울이 만나 '끝'을 의미합니다."
  },
  {
    "q": "滑る",
    "r": "すべる",
    "m": "미끄러지다, (스키 등을) 타다",
    "u": "동사(1그룹)",
    "e": "1. 道が 凍って いて、滑りやすいです。\n2. 冬休みに スキーを 滑りに 行きます。\n3. 試験に 滑って しまいました。",
    "tip": "[한자 풀이] 骨(뼈 골) + 氵(물 수). 매끄러운 뼈나 물 위를 미끄러지듯 나아가는 모습입니다."
  },
  {
    "q": "流れる",
    "r": "ながれる",
    "m": "흐르다, 떠내려가다",
    "u": "동사(2그룹)",
    "e": "1. 川の 水が 静かに 流れて います。\n2. 音楽が 店内に 流れて います。\n3. 涙が 頬を 流れました。",
    "tip": "[한자 풀이] 氵(물 수) + 充(가득할 충). 물이 가득 차서 낮은 곳으로 흘러가는 모양입니다."
  },
  {
    "q": "びっくりする",
    "r": "びっくりする",
    "m": "놀라다, 깜짝 놀라다",
    "u": "동사(3그룹)",
    "e": "1. 急に 大きな 音が して びっくりしました。\n2. 彼の 発表を 聞いて びっくりしました。\n3. びっくりさせないで ください。",
    "tip": "[한자 풀이] 喫(놀랄 끽) + 驚(놀랄 경). 놀라움을 들이마시고 경악한다는 의미입니다."
  },
  {
    "q": "珍しい",
    "r": "めずらしい",
    "m": "드물다, 희귀하다, 신기하다",
    "u": "이형용사",
    "e": "1. これは とても 珍しい 魚ですね。\n2. 雪が 降るのは 珍しいことです。\n3. 珍しい お土産を もらいました。",
    "tip": "[한자 풀이] 珍(보배 진). 구슬(玉)처럼 보기 드물고 귀한 상태를 나타냅니다."
  },
  {
    "q": "悔しい",
    "r": "く야しい",
    "m": "분하다, 후회스럽다",
    "u": "이형용사",
    "e": "1. 試合に 負けて とても 悔しいです。\n2. 悔しくて 一晩中 眠れませんでした。\n3. テ스트의 点数가 低くて 悔しいです。",
    "tip": "[한자 풀이] 悔(뉘우칠 회): 心(마음 심) + 毎(매양 매). 마음속에 늘 후회가 남는다는 뜻입니다."
  },
  {
    "q": "貼る",
    "r": "はる",
    "m": "붙이다, 접착하다",
    "u": "동사(1그룹)",
    "e": "1. 写真を 貼りたいですが、糊は ありますか。\n2. 壁に 新しい ポ스터를 貼りました。\n3. 封筒に 切手を 貼って 出しました。",
    "tip": "[한자 풀이] 貝(조개 패) + 占(차지할 점). 물건이나 돈을 어떤 자리에 붙여두는 모습에서 유래했습니다."
  },
  {
    "q": "針",
    "r": "はり",
    "m": "바늘, 침",
    "u": "명사",
    "e": "1. 針と 糸で ボタンを 付けました。\n2. 時計の 針が 12時を 指して います。\n3. 病院で 注射の 針は 痛くなかったです。",
    "tip": "[한자 풀이] 金(쇠 금) + 十(열 십). 금속으로 만든 뾰족한 바늘 모양을 형상화했습니다."
  },
  {
    "q": "はさみ",
    "r": "はさみ",
    "m": "가위",
    "u": "명사",
    "e": "1. はさみで 紙を 綺麗に 切りました。\n2. この はさみは 全然 切れません。\n3. 美容院で はさみの 音が 聞こえます。",
    "tip": "[한자 풀이] 鋏(가위 협): 金(쇠 금) + 夾(낄 협). 두 금속 사이에 물건을 끼워 자르는 도구입니다."
  },
  {
    "q": "筆",
    "r": "ふで",
    "m": "붓",
    "u": "명사",
    "e": "1. 筆で 名前を 大きく 書きました。\n2. 彼は 素晴らしい 筆を 持って います。\n3. 日本の 書道には 良い 붓이 必要です。",
    "tip": "[한자 풀이] 竹(대나무 죽) + 聿(붓 율). 대나무 대에 붓을 든 손의 모양이 합쳐진 글자입니다."
  },
  {
    "q": "細かい",
    "r": "こまかい",
    "m": "잘다, 미세하다, 세세하다",
    "u": "이형용사",
    "e": "1. 人参を 細かく 切って ください。\n2. 細かい お金が ありますか。\n3. この 説明は とても 細かいですね。",
    "tip": "[한자 풀이] 糸(실 사) + 田(밭 전). 실처럼 가늘고 밭의 흙처럼 잘게 부서진 모양을 나타냅니다."
  },
  {
    "q": "厚い",
    "r": "あつい",
    "m": "두껍다, 두툼하다",
    "u": "이형용사",
    "e": "1. この 本は とても 厚いです。\n2. お肉を 厚く 切りました。\n3. 冬は 厚い コートを 着ます。",
    "tip": "[한자 풀이] 厚(두터울 후). 언덕이나 기슭처럼 층이 겹겹이 쌓여 두터운 상태를 의미합니다."
  },
  {
    "q": "丁寧だ",
    "r": "ていねいだ",
    "m": "공손하다, 정중하다, 세심하다",
    "u": "나형용사",
    "e": "1. 丁寧な 言葉を 使いましょう。\n2. 彼は いつも 丁寧な 挨拶を します。\n3. 仕事が とても 丁寧で 素晴らしいです。",
    "tip": "[한자 풀이] 丁(고무래 정) + 寧(편안할 녕). 주의를 환기하기 위해 반복해서 치던 금속 악기에서 유래했습니다."
  },
  {
    "q": "汚れる",
    "r": "よごれる",
    "m": "더러워지다, 더럽혀지다",
    "u": "동사(2그룹)",
    "e": "1. 白い 服が 汚れて しまいました。\n2. 雨で 靴が 汚れました。\n3. 空気が 汚れて いるので、窓を 閉めます。",
    "tip": "[한자 풀이] 氵(물 수) + 于(어조사 우). 깨끗한 물에 불순물이 섞여 탁해진 모양을 나타냅니다."
  },
  {
    "q": "落ちる",
    "r": "おちる",
    "m": "떨어지다, 낙제하다, 빠지다",
    "u": "동사(2그룹)",
    "e": "1. 鞄が 椅子から 落ちました。\n2. 試験に 落ちて しまいました。\n3. この 汚れは なかなか 落ちません。",
    "tip": "[한자 풀이] 艹(풀 초) + 氵(물 수) + 各(각각 각). 나뭇잎이나 물방울이 아래로 떨어지는 모양에서 유래했습니다."
  }
]
